AUTHORS
Changelog
FAQ
INSTALL
LICENSE
MANIFEST.in
README
README.rst
THANKS
TODO
setup.cfg
setup.py
carrot/__init__.py
carrot/connection.py
carrot/messaging.py
carrot/serialization.py
carrot/utils.py
carrot.egg-info/PKG-INFO
carrot.egg-info/SOURCES.txt
carrot.egg-info/dependency_links.txt
carrot.egg-info/not-zip-safe
carrot.egg-info/requires.txt
carrot.egg-info/top_level.txt
carrot/backends/__init__.py
carrot/backends/base.py
carrot/backends/librabbitmq.py
carrot/backends/pikachu.py
carrot/backends/pyamqplib.py
carrot/backends/pystomp.py
carrot/backends/queue.py
docs/Makefile
docs/changelog.rst
docs/conf.py
docs/faq.rst
docs/index.rst
docs/introduction.rst
docs/rewrite.rst
docs/.build/doctrees/changelog.doctree
docs/.build/doctrees/environment.pickle
docs/.build/doctrees/faq.doctree
docs/.build/doctrees/index.doctree
docs/.build/doctrees/introduction.doctree
docs/.build/doctrees/reference/carrot.backends.base.doctree
docs/.build/doctrees/reference/carrot.backends.doctree
docs/.build/doctrees/reference/carrot.backends.pikachu.doctree
docs/.build/doctrees/reference/carrot.backends.pyamqplib.doctree
docs/.build/doctrees/reference/carrot.backends.pystomp.doctree
docs/.build/doctrees/reference/carrot.backends.queue.doctree
docs/.build/doctrees/reference/carrot.connection.doctree
docs/.build/doctrees/reference/carrot.messaging.doctree
docs/.build/doctrees/reference/carrot.serialization.doctree
docs/.build/doctrees/reference/carrot.utils.doctree
docs/.build/doctrees/reference/index.doctree
docs/.build/html/.buildinfo
docs/.build/html/changelog.html
docs/.build/html/faq.html
docs/.build/html/genindex.html
docs/.build/html/index.html
docs/.build/html/introduction.html
docs/.build/html/objects.inv
docs/.build/html/py-modindex.html
docs/.build/html/search.html
docs/.build/html/searchindex.js
docs/.build/html/_sources/changelog.txt
docs/.build/html/_sources/faq.txt
docs/.build/html/_sources/index.txt
docs/.build/html/_sources/introduction.txt
docs/.build/html/_sources/reference/carrot.backends.base.txt
docs/.build/html/_sources/reference/carrot.backends.pikachu.txt
docs/.build/html/_sources/reference/carrot.backends.pyamqplib.txt
