Metadata-Version: 1.0
Name: carrot
Version: 0.10.6
Summary: AMQP Messaging Framework for Python
Home-page: http://github.com/ask/carrot/
Author: Ask Solem
Author-email: ask@celeryproject.org
License: UNKNOWN
Platform: any
Classifier: Development Status :: 4 - Beta
Classifier: Framework :: Django
Classifier: Operating System :: OS Independent
Classifier: Programming Language :: Python
Classifier: License :: OSI Approved :: BSD License
Classifier: Intended Audience :: Developers
Classifier: Topic :: Communications
Classifier: Topic :: System :: Distributed Computing
Classifier: Topic :: Software Development :: Libraries :: Python Modules
